GrafanaSnapshot/__init__.py
GrafanaSnapshot/snapshot_face.py
GrafanaSnapshot/version.py
GrafanaSnapshot/feature/__init__.py
GrafanaSnapshot/feature/base.py
GrafanaSnapshot/feature/snapshots.py
tests/__init__.py
tests/test_delete_snapshot.py
tests/test_generate_snapshot.py
tests/test_get_snapshot_by_key.py
grafana_snapshot-0.2.dist-info/METADATA
grafana_snapshot-0.2.dist-info/WHEEL
grafana_snapshot-0.2.dist-info/top_level.txt
grafana_snapshot-0.2.dist-info/RECORD
