Metadata-Version: 2.1
Name: grafana-snapshot
Version: 0.2
Summary: Task a grafana snapshot
Home-page: https://github.com/ohmrefresh/grafana-snapshot.git
Author: Authapon Kongkaew, Nitipat Phiphatprathuang, Panchorn Lertvipada
Author-email: ohmrefresh@gmail.com, banknitipat@gmail.com, nonpcn@gmail.com
License: MIT
Platform: UNKNOWN
Classifier: Programming Language :: Python :: 3
Classifier: License :: OSI Approved :: MIT License
Classifier: Operating System :: OS Independent
Classifier: Programming Language :: Python
Classifier: Programming Language :: Python :: 2
Classifier: Programming Language :: Python :: 2.7
Classifier: Programming Language :: Python :: 3
Classifier: Programming Language :: Python :: 3.5
Classifier: Programming Language :: Python :: 3.6
Classifier: Programming Language :: Python :: 3.7
Classifier: Topic :: Software Development
Requires-Dist: requests
Requires-Dist: grafana-api
